{
  "build": {
    "development": {
      "developmentClient": true,
      "distribution": "internal",
      "env": {
        "EXPO_PUBLIC_API_BASE_URL": "http://177.44.248.81:3030"
      },
    },
    "preview": {
      "env": {
        "EXPO_PUBLIC_API_BASE_URL": "http://177.44.248.81:3030"
      },
      "android": {
        "buildType": "apk"
      }
    },
    "preview2": {
      "android": {
        "gradleCommand": ":app:assembleRelease"
      }
    },
    "preview4": {
      "distribution": "internal"
    },
    "production": {}
  }
}
